{
    "AX": {
        "error": 1e-20,
        "fit": "default",
        "references": [],
        "value": 1.0
    },
    "CDD": {
        "error": 0.0012816659884363896,
        "fit": "Weighted Mean",
        "reference_data": {
            "es": [
                0.0024642302229715687,
                0.002345206588372218,
                0.0023669986992378577,
                0.00256125066937573,
                0.002554542341610743,
                0.0023045956821545082,
                0.0023550209861646553
            ],
            "vs": [
                1.012922536236771,
                1.007376307738046,
                1.0020059626989304,
                1.0062791193044944,
                1.0101099513884275,
                1.0063426950213639,
                1.0066794411177642
            ],
            "xs": [
                1590548383.0,
                1590565788.0,
                1590582422.0,
                1590600067.0,
                1590617054.0,
                1590634255.0,
                1590656653.0
            ]
        },
        "reference_detector": "H1",
        "references": [
            {
                "exclude": "ok",
                "record_id": "a-02-J-2915",
                "uuid": "27ebce19-eaca-460d-b4ee-d66781567464"
            },
            {
                "exclude": "ok",
                "record_id": "a-02-J-2916",
                "uuid": "3d8e143e-070d-4a19-8298-d2556836047e"
            },
            {
                "exclude": "ok",
                "record_id": "a-02-J-2917",
                "uuid": "86b487a3-d31c-4644-be2d-fe22ad29113b"
            },
            {
                "exclude": "ok",
                "record_id": "a-02-J-2918",
                "uuid": "7ad0aadc-d818-4743-b440-94f61c6b58ec"
            },
            {
                "exclude": "ok",
                "record_id": "a-02-J-2919",
                "uuid": "a2d3217c-695f-4aa6-80a6-dd2e414652bc"
            },
            {
                "exclude": "ok",
                "record_id": "a-02-J-2920",
                "uuid": "72b0a7bd-bcf5-4892-bfbe-275a90f4f1b4"
            },
            {
                "exclude": "ok",
                "record_id": "a-02-J-2921",
                "uuid": "4574ab1c-a55e-4efa-8854-eacab7e8556f"
            }
        ],
        "reviewed": true,
        "standard_ratio": 295.5,
        "value": 1.0072814193206114
    },
    "H1": {
        "error": 1e-20,
        "fit": "default",
        "references": [],
        "value": 1.0
    },
    "H2": {
        "error": 1e-20,
        "fit": "default",
        "references": [],
        "value": 1.0
    },
    "L1": {
        "error": 1e-20,
        "fit": "default",
        "references": [],
        "value": 1.0
    },
    "L2": {
        "error": 1e-20,
        "fit": "default",
        "references": [],
        "value": 1.0
    }
}