{
    "Ar36": {
        "error": 0.00020717217355874297,
        "error_type": "",
        "fit": "previous",
        "references": [
            {
                "exclude": false,
                "record_id": "bu-FC-J-12346"
            }
        ],
        "value": 0.004213015983683863
    },
    "Ar37": {
        "error": 0.0063309177627292315,
        "error_type": "",
        "fit": "previous",
        "references": [
            {
                "exclude": false,
                "record_id": "bu-FC-J-12346"
            }
        ],
        "value": 0.04071087290291539
    },
    "Ar38": {
        "error": 0.0028980946255820804,
        "error_type": "",
        "fit": "previous",
        "references": [
            {
                "exclude": false,
                "record_id": "bu-FC-J-12346"
            }
        ],
        "value": 0.015722074674276245
    },
    "Ar39": {
        "error": 0.013272760294815273,
        "error_type": "",
        "fit": "previous",
        "references": [
            {
                "exclude": false,
                "record_id": "bu-FC-J-12346"
            }
        ],
        "value": 0.02384504778617627
    },
    "Ar40": {
        "error": 0.01042122872002197,
        "error_type": "",
        "fit": "previous",
        "references": [
            {
                "exclude": false,
                "record_id": "bu-FC-J-12346"
            }
        ],
        "value": 0.6854787456886874
    },
    "Ar41": {
        "error": 0.0027986149630877906,
        "error_type": "",
        "fit": "previous",
        "references": [
            {
                "exclude": false,
                "record_id": "bu-FC-J-12346"
            }
        ],
        "value": 0.04747257322060962
    }
}