{
    "Ar36": {
        "error": 0.00023825653663267255,
        "error_type": "",
        "fit": "previous",
        "references": [
            {
                "exclude": false,
                "record_id": "bu-FC-J-12102"
            }
        ],
        "value": 0.00560757118168948
    },
    "Ar37": {
        "error": 0.005556479183288359,
        "error_type": "",
        "fit": "previous",
        "references": [
            {
                "exclude": false,
                "record_id": "bu-FC-J-12102"
            }
        ],
        "value": 0.04423489987628436
    },
    "Ar38": {
        "error": 0.0030625184733163494,
        "error_type": "",
        "fit": "previous",
        "references": [
            {
                "exclude": false,
                "record_id": "bu-FC-J-12102"
            }
        ],
        "value": 0.024505411212712325
    },
    "Ar39": {
        "error": 0.01192812489186679,
        "error_type": "",
        "fit": "previous",
        "references": [
            {
                "exclude": false,
                "record_id": "bu-FC-J-12102"
            }
        ],
        "value": 0.040936020591662084
    },
    "Ar40": {
        "error": 0.0114689139363528,
        "error_type": "",
        "fit": "previous",
        "references": [
            {
                "exclude": false,
                "record_id": "bu-FC-J-12102"
            }
        ],
        "value": 1.0379144214632086
    },
    "Ar41": {
        "error": 0.0025436488755693327,
        "error_type": "",
        "fit": "previous",
        "references": [
            {
                "exclude": false,
                "record_id": "bu-FC-J-12102"
            }
        ],
        "value": 0.03321910796427793
    }
}