{
    "Ar36": {
        "error": 0.00018823142959238754,
        "error_type": "",
        "fit": "previous",
        "references": [
            {
                "exclude": false,
                "record_id": "bu-FC-J-12068"
            }
        ],
        "value": 0.003613360010021544
    },
    "Ar37": {
        "error": 0.006139849106504728,
        "error_type": "",
        "fit": "previous",
        "references": [
            {
                "exclude": false,
                "record_id": "bu-FC-J-12068"
            }
        ],
        "value": 0.03498989707392125
    },
    "Ar38": {
        "error": 0.0030026058500546224,
        "error_type": "",
        "fit": "previous",
        "references": [
            {
                "exclude": false,
                "record_id": "bu-FC-J-12068"
            }
        ],
        "value": 0.004051393732378391
    },
    "Ar39": {
        "error": 0.012651167951310865,
        "error_type": "",
        "fit": "previous",
        "references": [
            {
                "exclude": false,
                "record_id": "bu-FC-J-12068"
            }
        ],
        "value": 0.052705898037093336
    },
    "Ar40": {
        "error": 0.010372858995467596,
        "error_type": "",
        "fit": "previous",
        "references": [
            {
                "exclude": false,
                "record_id": "bu-FC-J-12068"
            }
        ],
        "value": 0.6032964114433594
    },
    "Ar41": {
        "error": 0.0025655247475921844,
        "error_type": "",
        "fit": "previous",
        "references": [
            {
                "exclude": false,
                "record_id": "bu-FC-J-12068"
            }
        ],
        "value": 0.03188378020016542
    }
}