{
    "Ar36": {
        "error": 0.0006840368391077227,
        "error_type": "SEM",
        "filter_outliers_dict": {
            "filter_outliers": true,
            "iterations": 1,
            "std_devs": 2
        },
        "fit": "Linear",
        "value": 0.08302656110114001
    },
    "Ar37": {
        "error": 0.01134555679128067,
        "error_type": "SEM",
        "filter_outliers_dict": {
            "filter_outliers": true,
            "iterations": 1,
            "std_devs": 2
        },
        "fit": "linear",
        "value": -0.036933810176131135
    },
    "Ar38": {
        "error": 0.0062699373860799715,
        "error_type": "SEM",
        "filter_outliers_dict": {
            "filter_outliers": true,
            "iterations": 1,
            "std_devs": 2
        },
        "fit": "linear",
        "value": 2.5259883358735413
    },
    "Ar39": {
        "error": 0.029000124438064514,
        "error_type": "SEM",
        "filter_outliers_dict": {
            "filter_outliers": true,
            "iterations": 1,
            "std_devs": 2
        },
        "fit": "Linear",
        "value": 197.6980649417482
    },
    "Ar40": {
        "error": 0.07155666380168221,
        "error_type": "SEM",
        "filter_outliers_dict": {
            "filter_outliers": true,
            "iterations": 1,
            "std_devs": 2
        },
        "fit": "Linear",
        "value": 1333.6824983332813
    },
    "Ar41": {
        "error": 0.0020618616451109958,
        "error_type": "SEM",
        "filter_outliers_dict": {
            "filter_outliers": true,
            "iterations": 1,
            "std_devs": 2
        },
        "fit": "Average",
        "value": 0.03793408899007603
    }
}